cronjobfilter/__init__.py
cronjobfilter/cronjobfilter.py
cronjobfilter-0.0.1.dist-info/LICENSE
cronjobfilter-0.0.1.dist-info/METADATA
cronjobfilter-0.0.1.dist-info/WHEEL
cronjobfilter-0.0.1.dist-info/top_level.txt
cronjobfilter-0.0.1.dist-info/RECORD
