Metadata-Version: 2.1
Name: cronjobfilter
Version: 0.0.1
Summary: A package will help to filter list of cronjobs which are coming under from date and to date.
Home-page: https://github.com/Solution4Problem/cronjobfilter/
Author: Priyesh Naik
Author-email: blackbeastfilo@live.com
License: UNKNOWN
Platform: UNKNOWN
Classifier: Programming Language :: Python :: 3.7
Classifier: License :: OSI Approved :: GNU General Public License v3 (GPLv3)
Requires-Dist: regex (>=2020.6.7)
Requires-Dist: requests (>=2)
